koruspy/AsyncResult.py
koruspy/Async_option.py
koruspy/Option.py
koruspy/Result.py
koruspy/__init__.py
koruspy/cythonprintln.cpython-312.so
koruspy/errors.py
koruspy/monadcollections.py
koruspy/py.typed
koruspy/build/lib.linux-aarch64-cpython-312/cythonprintln.cpython-312.so
koruspy/build/temp.linux-aarch64-cpython-312/data/data/com.termux/files/home/downloads/Koruspy-reboot/koruspy/printlnUtils/cythonprintln.o
koruspy/build/temp.linux-aarch64-cpython-312/data/data/org.smartide.code/files/home/projects/Koruspy/koruspy/printlnUtils/cythonprintln.o
koruspy/koruspy.egg-info/PKG-INFO
koruspy/koruspy.egg-info/SOURCES.txt
koruspy/koruspy.egg-info/dependency_links.txt
koruspy/koruspy.egg-info/top_level.txt
koruspy/printlnUtils/cythonprintln.c
koruspy/printlnUtils/cythonprintln.cpython-312.so
koruspy/printlnUtils/cythonprintln.html
koruspy/printlnUtils/cythonprintln.pyx
koruspy/printlnUtils/setup.py
koruspy/printlnUtils/build/lib.linux-aarch64-cpython-312/cythonprintln.cpython-312.so
koruspy/printlnUtils/build/temp.linux-aarch64-cpython-312/cythonprintln.o
koruspy-0.9.8.dist-info/WHEEL
koruspy-0.9.8.dist-info/METADATA
koruspy-0.9.8.dist-info/RECORD
