Metadata-Version: 2.4
Name: koruspy
Version: 0.9.8
Summary: Uma biblioteca inspirada em Rust e Kotlin para lidar com Option, Result, AsyncOption e coleções monadicas como SomeList, FrozenSomeList e LazyList
Requires-Python: >=3.10
